message_server_by_mokrenko-0.1.3.data/scripts/server_run
server/__init__.py
server/server.py
server/server_gui.py
server/client/__init__.py
server/client/add_contact.py
server/client/client_transport.py
server/client/database.py
server/client/del_contact.py
server/client/main_window.py
server/client/main_window_conv.py
server/client/start_dialog.py
server/client/temp_transport.py
server/common/__init__.py
server/common/decorators.py
server/common/descrptrs.py
server/common/errors.py
server/common/message.py
server/common/metaclasses.py
server/common/transport.py
server/common/utils.py
server/common/variables.py
server/logs/__init__.py
server/logs/config_client_log.py
server/logs/config_server_log.py
server/server/__init__.py
server/server/add_user.py
server/server/config_window.py
server/server/core.py
server/server/database.py
server/server/main_window.py
server/server/remove_user.py
server/server/stat_window.py
server/unit_tests/__init__.py
server/unit_tests/test_client.py
server/unit_tests/test_message.py
server/unit_tests/test_server.py
message_server_by_mokrenko-0.1.3.dist-info/METADATA
message_server_by_mokrenko-0.1.3.dist-info/WHEEL
message_server_by_mokrenko-0.1.3.dist-info/top_level.txt
message_server_by_mokrenko-0.1.3.dist-info/RECORD
