Metadata-Version: 2.1
Name: message-server-by-mokrenko
Version: 0.1.3
Summary: Message Server Package
Home-page: UNKNOWN
Author: Vladimir Mokrenko
Author-email: v.v.mokrenko@gmail.com
License: UNKNOWN
Platform: UNKNOWN
Requires-Dist: PyQt5
Requires-Dist: sqlalchemy
Requires-Dist: pycryptodome
Requires-Dist: pycryptodomex
